chronver/__init__.py
chronver/git.py
chronver/pkg_info.py
chronver/setuptools_hooks.py
chronver-20240318.230216.dist-info/LICENSE
chronver-20240318.230216.dist-info/METADATA
chronver-20240318.230216.dist-info/WHEEL
chronver-20240318.230216.dist-info/entry_points.txt
chronver-20240318.230216.dist-info/top_level.txt
chronver-20240318.230216.dist-info/RECORD
