Metadata-Version: 2.1
Name: chronver
Version: 20240318.230216
Summary: Setuptools plugin for chronological versions from Git
Author-email: RadiaSoft LLC <pip@pykern.org>
Project-URL: Homepage, https://github.com/radiasoft/chronver
Keywords: git,plugin,scm,setuptools,vcs,version
Classifier: Development Status :: 3 - Alpha
Classifier: License :: OSI Approved :: Apache Software License
Classifier: Programming Language :: Python
Classifier: Programming Language :: Python :: Implementation :: CPython
Requires-Python: >=3.8
License-File: LICENSE
Requires-Dist: build >=1
Requires-Dist: setuptools >=61
